README.md
setup.py
ltcn/LTCN.py
ltcn/__init__.py
ltcn.egg-info/PKG-INFO
ltcn.egg-info/SOURCES.txt
ltcn.egg-info/dependency_links.txt
ltcn.egg-info/requires.txt
ltcn.egg-info/top_level.txt