Metadata-Version: 1.1
Name: ltcn
Version: 0.1.0
Summary: Long-term Cognitive Networks for pattern classification
Home-page: https://github.com/gnapoles/ltcn-classifier
Author: Gonzalo Nápoles
Author-email: g.r.napoles@uvt.nl
License: MIT License
Platform: UNKNOWN
Classifier: Development Status :: 1 - Planning
Classifier: Intended Audience :: Science/Research
Classifier: License :: OSI Approved :: MIT License
Classifier: Operating System :: Microsoft :: Windows
Classifier: Operating System :: MacOS
Classifier: Programming Language :: Python :: 3.8
